[{"line":2,"elements":[{"start_timestamp":"2022-06-15T19:48:37.943Z","line":3,"name":"aaa","description":"","id":"aaa;aaa","type":"scenario","keyword":"Scenario","steps":[{"result":{"error_message":"org.openqa.selenium.NoSuchElementException: no such element: Unable to locate element: {\"method\":\"xpath\",\"selector\":\"//span[@class='close-icon']\"}\n  (Session info: chrome=102.0.5005.115)\nFor documentation on this error, please visit: https://selenium.dev/exceptions/#no_such_element\nBuild info: version: '4.1.1', revision: 'e8fcc2cecf'\nSystem info: host: 'LAPTOP-KJ47EG41', ip: '192.168.0.14', os.name: 'Windows 10', os.arch: 'amd64', os.version: '10.0', java.version: '16.0.1'\nDriver info: org.openqa.selenium.chrome.ChromeDriver\nCommand: [b1ed29080034aabf0b17aecf12347010, findElement {using=xpath, value=//span[@class='close-icon']}]\nCapabilities {acceptInsecureCerts: false, browserName: chrome, browserVersion: 102.0.5005.115, chrome: {chromedriverVersion: 102.0.5005.61 (0e59bcc00cc4..., userDataDir: C:\\Users\\rayku\\AppData\\Loca...}, goog:chromeOptions: {debuggerAddress: localhost:56118}, javascriptEnabled: true, networkConnectionEnabled: false, pageLoadStrategy: normal, platform: WINDOWS, platformName: WINDOWS, proxy: Proxy(), se:cdp: ws://localhost:56118/devtoo..., se:cdpVersion: 102.0.5005.115, setWindowRect: true, strictFileInteractability: false, timeouts: {implicit: 0, pageLoad: 300000, script: 30000}, unhandledPromptBehavior: dismiss and notify, webauthn:extension:credBlob: true, webauthn:extension:largeBlob: true, webauthn:virtualAuthenticators: true}\nSession ID: b1ed29080034aabf0b17aecf12347010\r\n\tat java.base/jdk.internal.reflect.NativeConstructorAccessorImpl.newInstance0(Native Method)\r\n\tat java.base/jdk.internal.reflect.NativeConstructorAccessorImpl.newInstance(NativeConstructorAccessorImpl.java:78)\r\n\tat java.base/jdk.internal.reflect.DelegatingConstructorAccessorImpl.newInstance(DelegatingConstructorAccessorImpl.java:45)\r\n\tat java.base/java.lang.reflect.Constructor.newInstanceWithCaller(Constructor.java:499)\r\n\tat java.base/java.lang.reflect.Constructor.newInstance(Constructor.java:480)\r\n\tat org.openqa.selenium.remote.codec.w3c.W3CHttpResponseCodec.createException(W3CHttpResponseCodec.java:200)\r\n\tat org.openqa.selenium.remote.codec.w3c.W3CHttpResponseCodec.decode(W3CHttpResponseCodec.java:133)\r\n\tat org.openqa.selenium.remote.codec.w3c.W3CHttpResponseCodec.decode(W3CHttpResponseCodec.java:53)\r\n\tat org.openqa.selenium.remote.HttpCommandExecutor.execute(HttpCommandExecutor.java:184)\r\n\tat org.openqa.selenium.remote.service.DriverCommandExecutor.invokeExecute(DriverCommandExecutor.java:167)\r\n\tat org.openqa.selenium.remote.service.DriverCommandExecutor.execute(DriverCommandExecutor.java:142)\r\n\tat org.openqa.selenium.remote.RemoteWebDriver.execute(RemoteWebDriver.java:543)\r\n\tat org.openqa.selenium.remote.ElementLocation$ElementFinder$2.findElement(ElementLocation.java:162)\r\n\tat org.openqa.selenium.remote.ElementLocation.findElement(ElementLocation.java:60)\r\n\tat org.openqa.selenium.remote.RemoteWebDriver.findElement(RemoteWebDriver.java:367)\r\n\tat org.openqa.selenium.remote.RemoteWebDriver.findElement(RemoteWebDriver.java:359)\r\n\tat stepdefinitions.hbSteps.user_enter_site(hbSteps.java:25)\r\n\tat ✽.user enter site(file:///C:/Users/rayku/IdeaProjects/hepsiburadaTask/./src/test/resources/hb.feature:4)\r\n","duration":14106545300,"status":"failed"},"line":4,"name":"user enter site","match":{"location":"stepdefinitions.hbSteps.user_enter_site()"},"keyword":"Given "}],"tags":[{"name":"@aaaaa"}]}],"name":"aaa","description":"","id":"aaa","keyword":"Feature","uri":"file:src/test/resources/hb.feature","tags":[{"name":"@aaaaa","type":"Tag","location":{"line":1,"column":1}}]}]